propypika/__init__.py
propypika/analytics.py
propypika/dialects.py
propypika/enums.py
propypika/functions.py
propypika/pseudocolumns.py
propypika/py.typed
propypika/queries.py
propypika/terms.py
propypika/utils.py
propypika/clickhouse/__init__.py
propypika/clickhouse/array.py
propypika/clickhouse/condition.py
propypika/clickhouse/dates_and_times.py
propypika/clickhouse/nullable_arg.py
propypika/clickhouse/search_string.py
propypika/clickhouse/type_conversion.py
pypika/__init__.py
pypika/analytics.py
pypika/dialects.py
pypika/enums.py
pypika/functions.py
pypika/pseudocolumns.py
pypika/py.typed
pypika/queries.py
pypika/terms.py
pypika/utils.py
pypika/clickhouse/__init__.py
pypika/clickhouse/array.py
pypika/clickhouse/condition.py
pypika/clickhouse/dates_and_times.py
pypika/clickhouse/nullable_arg.py
pypika/clickhouse/search_string.py
pypika/clickhouse/type_conversion.py
ProPyPika-0.48.10.dist-info/LICENSE.txt
ProPyPika-0.48.10.dist-info/METADATA
ProPyPika-0.48.10.dist-info/WHEEL
ProPyPika-0.48.10.dist-info/top_level.txt
ProPyPika-0.48.10.dist-info/RECORD
